{"name":"GOLF CLUB DE DUMBEA","code":107,"terrains":[{"name":"18 trous \/ Dumb&eacute;a","code":"01","tees":[{"color":"red","menSSS":"67,4","menSlope":"120","womenSSS":"72,6","womenSlope":"134","holes":{"1":{"num":"1","par":"4","hcp":"1","distance":"323"},"2":{"num":"2","par":"4","hcp":"11","distance":"236"},"3":{"num":"3","par":"3","hcp":"9","distance":"140"},"4":{"num":"4","par":"4","hcp":"5","distance":"261"},"5":{"num":"5","par":"5","hcp":"17","distance":"409"},"6":{"num":"6","par":"4","hcp":"3","distance":"300"},"7":{"num":"7","par":"4","hcp":"7","distance":"313"},"8":{"num":"8","par":"5","hcp":"13","distance":"349"},"9":{"num":"9","par":"3","hcp":"15","distance":"86"},"10":{"num":"10","par":"4","hcp":"12","distance":"269"},"11":{"num":"11","par":"3","hcp":"16","distance":"121"},"12":{"num":"12","par":"4","hcp":"8","distance":"316"},"13":{"num":"13","par":"4","hcp":"14","distance":"325"},"14":{"num":"14","par":"4","hcp":"10","distance":"319"},"15":{"num":"15","par":"5","hcp":"18","distance":"413"},"16":{"num":"16","par":"3","hcp":"2","distance":"98"},"17":{"num":"17","par":"5","hcp":"4","distance":"435"},"18":{"num":"18","par":"4","hcp":"6","distance":"266"}}},{"color":"blue","menSSS":"69,2","menSlope":"123","womenSSS":"75","womenSlope":"141","holes":{"1":{"num":"1","par":"4","hcp":"1","distance":"325"},"2":{"num":"2","par":"4","hcp":"11","distance":"292"},"3":{"num":"3","par":"3","hcp":"9","distance":"147"},"4":{"num":"4","par":"4","hcp":"5","distance":"309"},"5":{"num":"5","par":"5","hcp":"17","distance":"409"},"6":{"num":"6","par":"4","hcp":"3","distance":"331"},"7":{"num":"7","par":"4","hcp":"7","distance":"329"},"8":{"num":"8","par":"5","hcp":"13","distance":"377"},"9":{"num":"9","par":"3","hcp":"15","distance":"144"},"10":{"num":"10","par":"4","hcp":"12","distance":"279"},"11":{"num":"11","par":"3","hcp":"16","distance":"121"},"12":{"num":"12","par":"4","hcp":"8","distance":"329"},"13":{"num":"13","par":"4","hcp":"14","distance":"338"},"14":{"num":"14","par":"4","hcp":"10","distance":"337"},"15":{"num":"15","par":"5","hcp":"18","distance":"429"},"16":{"num":"16","par":"3","hcp":"2","distance":"122"},"17":{"num":"17","par":"5","hcp":"4","distance":"450"},"18":{"num":"18","par":"4","hcp":"6","distance":"283"}}},{"color":"yellow","menSSS":"70,4","menSlope":"126","womenSSS":"76,4","womenSlope":"145","holes":{"1":{"num":"1","par":"4","hcp":"1","distance":"325"},"2":{"num":"2","par":"4","hcp":"11","distance":"292"},"3":{"num":"3","par":"3","hcp":"9","distance":"147"},"4":{"num":"4","par":"4","hcp":"5","distance":"316"},"5":{"num":"5","par":"5","hcp":"17","distance":"409"},"6":{"num":"6","par":"4","hcp":"3","distance":"342"},"7":{"num":"7","par":"4","hcp":"7","distance":"336"},"8":{"num":"8","par":"5","hcp":"13","distance":"427"},"9":{"num":"9","par":"3","hcp":"15","distance":"144"},"10":{"num":"10","par":"4","hcp":"12","distance":"293"},"11":{"num":"11","par":"3","hcp":"16","distance":"156"},"12":{"num":"12","par":"4","hcp":"8","distance":"342"},"13":{"num":"13","par":"4","hcp":"14","distance":"352"},"14":{"num":"14","par":"4","hcp":"10","distance":"349"},"15":{"num":"15","par":"5","hcp":"18","distance":"443"},"16":{"num":"16","par":"3","hcp":"2","distance":"131"},"17":{"num":"17","par":"5","hcp":"4","distance":"495"},"18":{"num":"18","par":"4","hcp":"6","distance":"283"}}},{"color":"white","menSSS":"73","menSlope":"134","womenSSS":null,"womenSlope":null,"holes":{"1":{"num":"1","par":"4","hcp":"1","distance":"366"},"2":{"num":"2","par":"4","hcp":"11","distance":"313"},"3":{"num":"3","par":"3","hcp":"9","distance":"156"},"4":{"num":"4","par":"4","hcp":"5","distance":"371"},"5":{"num":"5","par":"5","hcp":"17","distance":"453"},"6":{"num":"6","par":"4","hcp":"3","distance":"357"},"7":{"num":"7","par":"4","hcp":"7","distance":"372"},"8":{"num":"8","par":"5","hcp":"13","distance":"438"},"9":{"num":"9","par":"3","hcp":"15","distance":"172"},"10":{"num":"10","par":"4","hcp":"12","distance":"326"},"11":{"num":"11","par":"3","hcp":"16","distance":"156"},"12":{"num":"12","par":"4","hcp":"8","distance":"367"},"13":{"num":"13","par":"4","hcp":"14","distance":"366"},"14":{"num":"14","par":"4","hcp":"10","distance":"363"},"15":{"num":"15","par":"5","hcp":"18","distance":"460"},"16":{"num":"16","par":"3","hcp":"2","distance":"182"},"17":{"num":"17","par":"5","hcp":"4","distance":"524"},"18":{"num":"18","par":"4","hcp":"6","distance":"336"}}},{"color":"black","menSSS":"74,4","menSlope":"137","womenSSS":null,"womenSlope":null,"holes":{"1":{"num":"1","par":"4","hcp":"1","distance":"377"},"2":{"num":"2","par":"4","hcp":"11","distance":"326"},"3":{"num":"3","par":"3","hcp":"9","distance":"156"},"4":{"num":"4","par":"4","hcp":"5","distance":"387"},"5":{"num":"5","par":"5","hcp":"17","distance":"469"},"6":{"num":"6","par":"4","hcp":"3","distance":"371"},"7":{"num":"7","par":"4","hcp":"7","distance":"392"},"8":{"num":"8","par":"5","hcp":"13","distance":"448"},"9":{"num":"9","par":"3","hcp":"15","distance":"197"},"10":{"num":"10","par":"4","hcp":"12","distance":"326"},"11":{"num":"11","par":"3","hcp":"16","distance":"156"},"12":{"num":"12","par":"4","hcp":"8","distance":"381"},"13":{"num":"13","par":"4","hcp":"14","distance":"380"},"14":{"num":"14","par":"4","hcp":"10","distance":"379"},"15":{"num":"15","par":"5","hcp":"18","distance":"475"},"16":{"num":"16","par":"3","hcp":"2","distance":"198"},"17":{"num":"17","par":"5","hcp":"4","distance":"558"},"18":{"num":"18","par":"4","hcp":"6","distance":"348"}}}]}]}