{"name":"GOLF DE MOURMELON (CSAG)","code":1766,"terrains":[{"name":"18 trous \/ Napol&eacute;on III","code":"01","tees":[{"color":"red","menSSS":"66","menSlope":"124","womenSSS":"70,8","womenSlope":"127","holes":{"1":{"num":"1","par":"5","hcp":"6","distance":"406"},"2":{"num":"2","par":"4","hcp":"17","distance":"252"},"3":{"num":"3","par":"4","hcp":"2","distance":"295"},"4":{"num":"4","par":"3","hcp":"15","distance":"125"},"5":{"num":"5","par":"4","hcp":"11","distance":"257"},"6":{"num":"6","par":"4","hcp":"7","distance":"290"},"7":{"num":"7","par":"5","hcp":"10","distance":"394"},"8":{"num":"8","par":"4","hcp":"14","distance":"254"},"9":{"num":"9","par":"3","hcp":"18","distance":"93"},"10":{"num":"10","par":"3","hcp":"16","distance":"133"},"11":{"num":"11","par":"4","hcp":"4","distance":"291"},"12":{"num":"12","par":"4","hcp":"9","distance":"272"},"13":{"num":"13","par":"4","hcp":"8","distance":"249"},"14":{"num":"14","par":"5","hcp":"3","distance":"409"},"15":{"num":"15","par":"4","hcp":"1","distance":"277"},"16":{"num":"16","par":"4","hcp":"13","distance":"272"},"17":{"num":"17","par":"4","hcp":"12","distance":"228"},"18":{"num":"18","par":"4","hcp":"5","distance":"268"}}},{"color":"blue","menSSS":"67,6","menSlope":"127","womenSSS":"73,1","womenSlope":"129","holes":{"1":{"num":"1","par":"5","hcp":"6","distance":"426"},"2":{"num":"2","par":"4","hcp":"17","distance":"262"},"3":{"num":"3","par":"4","hcp":"2","distance":"295"},"4":{"num":"4","par":"3","hcp":"15","distance":"135"},"5":{"num":"5","par":"4","hcp":"11","distance":"277"},"6":{"num":"6","par":"4","hcp":"7","distance":"309"},"7":{"num":"7","par":"5","hcp":"10","distance":"394"},"8":{"num":"8","par":"4","hcp":"14","distance":"293"},"9":{"num":"9","par":"3","hcp":"18","distance":"93"},"10":{"num":"10","par":"3","hcp":"16","distance":"141"},"11":{"num":"11","par":"4","hcp":"4","distance":"316"},"12":{"num":"12","par":"4","hcp":"9","distance":"285"},"13":{"num":"13","par":"4","hcp":"8","distance":"249"},"14":{"num":"14","par":"5","hcp":"3","distance":"450"},"15":{"num":"15","par":"4","hcp":"1","distance":"320"},"16":{"num":"16","par":"4","hcp":"13","distance":"282"},"17":{"num":"17","par":"4","hcp":"12","distance":"248"},"18":{"num":"18","par":"4","hcp":"5","distance":"314"}}},{"color":"yellow","menSSS":"70","menSlope":"132","womenSSS":"75,9","womenSlope":"135","holes":{"1":{"num":"1","par":"5","hcp":"6","distance":"470"},"2":{"num":"2","par":"4","hcp":"17","distance":"279"},"3":{"num":"3","par":"4","hcp":"2","distance":"313"},"4":{"num":"4","par":"3","hcp":"15","distance":"145"},"5":{"num":"5","par":"4","hcp":"11","distance":"300"},"6":{"num":"6","par":"4","hcp":"7","distance":"327"},"7":{"num":"7","par":"5","hcp":"10","distance":"450"},"8":{"num":"8","par":"4","hcp":"14","distance":"293"},"9":{"num":"9","par":"3","hcp":"18","distance":"130"},"10":{"num":"10","par":"3","hcp":"16","distance":"155"},"11":{"num":"11","par":"4","hcp":"4","distance":"340"},"12":{"num":"12","par":"4","hcp":"9","distance":"305"},"13":{"num":"13","par":"4","hcp":"8","distance":"262"},"14":{"num":"14","par":"5","hcp":"3","distance":"478"},"15":{"num":"15","par":"4","hcp":"1","distance":"365"},"16":{"num":"16","par":"4","hcp":"13","distance":"292"},"17":{"num":"17","par":"4","hcp":"12","distance":"302"},"18":{"num":"18","par":"4","hcp":"5","distance":"351"}}},{"color":"white","menSSS":"70,9","menSlope":"131","womenSSS":"77,2","womenSlope":"138","holes":{"1":{"num":"1","par":"5","hcp":"6","distance":"478"},"2":{"num":"2","par":"4","hcp":"17","distance":"288"},"3":{"num":"3","par":"4","hcp":"2","distance":"313"},"4":{"num":"4","par":"3","hcp":"15","distance":"155"},"5":{"num":"5","par":"4","hcp":"11","distance":"300"},"6":{"num":"6","par":"4","hcp":"7","distance":"345"},"7":{"num":"7","par":"5","hcp":"10","distance":"450"},"8":{"num":"8","par":"4","hcp":"14","distance":"344"},"9":{"num":"9","par":"3","hcp":"18","distance":"130"},"10":{"num":"10","par":"3","hcp":"16","distance":"155"},"11":{"num":"11","par":"4","hcp":"4","distance":"351"},"12":{"num":"12","par":"4","hcp":"9","distance":"320"},"13":{"num":"13","par":"4","hcp":"8","distance":"262"},"14":{"num":"14","par":"5","hcp":"3","distance":"501"},"15":{"num":"15","par":"4","hcp":"1","distance":"377"},"16":{"num":"16","par":"4","hcp":"13","distance":"302"},"17":{"num":"17","par":"4","hcp":"12","distance":"322"},"18":{"num":"18","par":"4","hcp":"5","distance":"369"}}},{"color":"black","menSSS":"70,9","menSlope":"131","womenSSS":"77,2","womenSlope":"138","holes":{"1":{"num":"1","par":"5","hcp":"6","distance":"478"},"2":{"num":"2","par":"4","hcp":"17","distance":"288"},"3":{"num":"3","par":"4","hcp":"2","distance":"313"},"4":{"num":"4","par":"3","hcp":"15","distance":"155"},"5":{"num":"5","par":"4","hcp":"11","distance":"300"},"6":{"num":"6","par":"4","hcp":"7","distance":"345"},"7":{"num":"7","par":"5","hcp":"10","distance":"450"},"8":{"num":"8","par":"4","hcp":"14","distance":"344"},"9":{"num":"9","par":"3","hcp":"18","distance":"130"},"10":{"num":"10","par":"3","hcp":"16","distance":"155"},"11":{"num":"11","par":"4","hcp":"4","distance":"351"},"12":{"num":"12","par":"4","hcp":"9","distance":"320"},"13":{"num":"13","par":"4","hcp":"8","distance":"262"},"14":{"num":"14","par":"5","hcp":"3","distance":"501"},"15":{"num":"15","par":"4","hcp":"1","distance":"377"},"16":{"num":"16","par":"4","hcp":"13","distance":"302"},"17":{"num":"17","par":"4","hcp":"12","distance":"322"},"18":{"num":"18","par":"4","hcp":"5","distance":"369"}}}]},{"name":"9 trous \/ P&amp;P Mourmelon","code":"03","tees":[{"color":"red","menSSS":"27","menSlope":"25","womenSSS":"27","womenSlope":"25","holes":{"1":{"num":"1","par":"3","hcp":"6","distance":"61"},"2":{"num":"2","par":"3","hcp":"2","distance":"77"},"3":{"num":"3","par":"3","hcp":"5","distance":"84"},"4":{"num":"4","par":"3","hcp":"3","distance":"68"},"5":{"num":"5","par":"3","hcp":"9","distance":"58"},"6":{"num":"6","par":"3","hcp":"7","distance":"57"},"7":{"num":"7","par":"3","hcp":"1","distance":"70"},"8":{"num":"8","par":"3","hcp":"8","distance":"52"},"9":{"num":"9","par":"3","hcp":"4","distance":"72"}}},{"color":"blue","menSSS":"27","menSlope":"25","womenSSS":"27","womenSlope":"25","holes":{"1":{"num":"1","par":"3","hcp":"6","distance":"61"},"2":{"num":"2","par":"3","hcp":"2","distance":"77"},"3":{"num":"3","par":"3","hcp":"5","distance":"84"},"4":{"num":"4","par":"3","hcp":"3","distance":"68"},"5":{"num":"5","par":"3","hcp":"9","distance":"58"},"6":{"num":"6","par":"3","hcp":"7","distance":"57"},"7":{"num":"7","par":"3","hcp":"1","distance":"70"},"8":{"num":"8","par":"3","hcp":"8","distance":"52"},"9":{"num":"9","par":"3","hcp":"4","distance":"72"}}},{"color":"yellow","menSSS":"27","menSlope":"25","womenSSS":"27","womenSlope":"25","holes":{"1":{"num":"1","par":"3","hcp":"6","distance":"61"},"2":{"num":"2","par":"3","hcp":"2","distance":"77"},"3":{"num":"3","par":"3","hcp":"5","distance":"84"},"4":{"num":"4","par":"3","hcp":"3","distance":"68"},"5":{"num":"5","par":"3","hcp":"9","distance":"58"},"6":{"num":"6","par":"3","hcp":"7","distance":"57"},"7":{"num":"7","par":"3","hcp":"1","distance":"70"},"8":{"num":"8","par":"3","hcp":"8","distance":"52"},"9":{"num":"9","par":"3","hcp":"4","distance":"72"}}},{"color":"white","menSSS":"27","menSlope":"25","womenSSS":"27","womenSlope":"25","holes":{"1":{"num":"1","par":"3","hcp":"6","distance":"61"},"2":{"num":"2","par":"3","hcp":"2","distance":"77"},"3":{"num":"3","par":"3","hcp":"5","distance":"84"},"4":{"num":"4","par":"3","hcp":"3","distance":"68"},"5":{"num":"5","par":"3","hcp":"9","distance":"58"},"6":{"num":"6","par":"3","hcp":"7","distance":"57"},"7":{"num":"7","par":"3","hcp":"1","distance":"70"},"8":{"num":"8","par":"3","hcp":"8","distance":"52"},"9":{"num":"9","par":"3","hcp":"4","distance":"72"}}},{"color":"black","menSSS":"27","menSlope":"25","womenSSS":"27","womenSlope":"25","holes":{"1":{"num":"1","par":"3","hcp":"6","distance":"61"},"2":{"num":"2","par":"3","hcp":"2","distance":"77"},"3":{"num":"3","par":"3","hcp":"5","distance":"84"},"4":{"num":"4","par":"3","hcp":"3","distance":"68"},"5":{"num":"5","par":"3","hcp":"9","distance":"58"},"6":{"num":"6","par":"3","hcp":"7","distance":"57"},"7":{"num":"7","par":"3","hcp":"1","distance":"70"},"8":{"num":"8","par":"3","hcp":"8","distance":"52"},"9":{"num":"9","par":"3","hcp":"4","distance":"72"}}}]}]}