{"name":"GOLF DE BOUC BEL AIR","code":2237,"terrains":[{"name":"9 trous \/ Green City P&amp;P","code":"01","tees":[{"color":"red","menSSS":"27","menSlope":"25","womenSSS":"27","womenSlope":"25","holes":{"1":{"num":"1","par":"3","hcp":"2","distance":"41"},"2":{"num":"2","par":"3","hcp":"9","distance":"59"},"3":{"num":"3","par":"3","hcp":"8","distance":"64"},"4":{"num":"4","par":"3","hcp":"4","distance":"42"},"5":{"num":"5","par":"3","hcp":"7","distance":"77"},"6":{"num":"6","par":"3","hcp":"5","distance":"63"},"7":{"num":"7","par":"3","hcp":"1","distance":"80"},"8":{"num":"8","par":"3","hcp":"6","distance":"73"},"9":{"num":"9","par":"3","hcp":"3","distance":"53"}}},{"color":"blue","menSSS":"27","menSlope":"25","womenSSS":"27","womenSlope":"25","holes":{"1":{"num":"1","par":"3","hcp":"2","distance":"41"},"2":{"num":"2","par":"3","hcp":"9","distance":"59"},"3":{"num":"3","par":"3","hcp":"8","distance":"64"},"4":{"num":"4","par":"3","hcp":"4","distance":"42"},"5":{"num":"5","par":"3","hcp":"7","distance":"77"},"6":{"num":"6","par":"3","hcp":"5","distance":"63"},"7":{"num":"7","par":"3","hcp":"1","distance":"80"},"8":{"num":"8","par":"3","hcp":"6","distance":"73"},"9":{"num":"9","par":"3","hcp":"3","distance":"53"}}},{"color":"yellow","menSSS":"27","menSlope":"25","womenSSS":"27","womenSlope":"25","holes":{"1":{"num":"1","par":"3","hcp":"2","distance":"41"},"2":{"num":"2","par":"3","hcp":"9","distance":"59"},"3":{"num":"3","par":"3","hcp":"8","distance":"64"},"4":{"num":"4","par":"3","hcp":"4","distance":"42"},"5":{"num":"5","par":"3","hcp":"7","distance":"77"},"6":{"num":"6","par":"3","hcp":"5","distance":"63"},"7":{"num":"7","par":"3","hcp":"1","distance":"80"},"8":{"num":"8","par":"3","hcp":"6","distance":"73"},"9":{"num":"9","par":"3","hcp":"3","distance":"53"}}},{"color":"white","menSSS":"27","menSlope":"25","womenSSS":"27","womenSlope":"25","holes":{"1":{"num":"1","par":"3","hcp":"2","distance":"41"},"2":{"num":"2","par":"3","hcp":"9","distance":"59"},"3":{"num":"3","par":"3","hcp":"8","distance":"64"},"4":{"num":"4","par":"3","hcp":"4","distance":"42"},"5":{"num":"5","par":"3","hcp":"7","distance":"77"},"6":{"num":"6","par":"3","hcp":"5","distance":"63"},"7":{"num":"7","par":"3","hcp":"1","distance":"80"},"8":{"num":"8","par":"3","hcp":"6","distance":"73"},"9":{"num":"9","par":"3","hcp":"3","distance":"53"}}},{"color":"black","menSSS":"27","menSlope":"25","womenSSS":"27","womenSlope":"25","holes":{"1":{"num":"1","par":"3","hcp":"2","distance":"41"},"2":{"num":"2","par":"3","hcp":"9","distance":"59"},"3":{"num":"3","par":"3","hcp":"8","distance":"64"},"4":{"num":"4","par":"3","hcp":"4","distance":"42"},"5":{"num":"5","par":"3","hcp":"7","distance":"77"},"6":{"num":"6","par":"3","hcp":"5","distance":"63"},"7":{"num":"7","par":"3","hcp":"1","distance":"80"},"8":{"num":"8","par":"3","hcp":"6","distance":"73"},"9":{"num":"9","par":"3","hcp":"3","distance":"53"}}}]}]}